Metadata-Version: 2.1
Name: cocoatree
Version: 0.0.0a0.dev0
Summary: Awesome coevolution stuff
Home-page: https://github.com/FIXME
Author: William Schmitt
Author-email: nelle.varoquaux@gmail.com
License: UNKNOWN
Project-URL: Bug Reports, https://github.com/FIXME
Project-URL: Source, https://github.com/FIXME/
Keywords: mystery
Platform: UNKNOWN
Classifier: Development Status :: 3 - Alpha
Classifier: Topic :: Software Development :: Build Tools
Classifier: License :: OSI Approved :: MIT License
Classifier: Programming Language :: Python :: 3.8
Classifier: Programming Language :: Python :: 3.9
Requires-Python: >=3.8, <4
Provides-Extra: dev
Provides-Extra: test
